badgey/__init__.py
badgey/__version__.py
badgey/_base.py
badgey/badges.py
badgey/colormap.py
badgey/mixins.py
badgey-0.2.3.dist-info/entry_points.txt
badgey-0.2.3.dist-info/LICENSE
badgey-0.2.3.dist-info/WHEEL
badgey-0.2.3.dist-info/METADATA
badgey-0.2.3.dist-info/RECORD
