Metadata-Version: 2.1
Name: badgey
Version: 0.2.3
Summary: A library and a CLI to locally generate project badges
License: MIT
Author: Ruben Di Battista
Author-email: rubendibattista@gmail.com
Requires-Python: >=3.7,<4.0
Classifier: Development Status :: 4 - Beta
Classifier: Environment :: Console
Classifier: Intended Audience :: Developers
Classifier: License :: OSI Approved :: MIT License
Classifier: Programming Language :: Python :: 3
Classifier: Programming Language :: Python :: 3.7
Classifier: Programming Language :: Python :: 3.8
Classifier: Programming Language :: Python :: 3.9
Classifier: Topic :: Software Development :: Documentation
Classifier: Topic :: Software Development :: Version Control :: Git
Requires-Dist: GitPython (>=3.1.20,<4.0.0)
Requires-Dist: docopt (>=0.6.2,<0.7.0)
Requires-Dist: matplotlib (>=3.4.3,<4.0.0)
Requires-Dist: pybadges (>=2.2.1,<3.0.0)
